{"cartas":{"1":{"numero":1,"sigla_edicao":"st2k","edicao":"Starter 2000","cod":"1st2kde","idioma":"de","nome":"Himmlischer Segen","ataque":"","resistencia":"","lealdade":"","mana":"2W","mana_convertida":"3","raridade":"Special","artista":"Mark Zug","link":"http:\/\/magiccards.info\/st2k\/de\/1.html","imagem_src":"http:\/\/magiccards.info\/scans\/de\/st2k\/1.jpg","imagem_local":"st2k\/de\/1.jpg","descricao":"Eine Kreatur deiner Wahl erh\u00e4lt +3\/+3 und Flugf\u00e4higkeit bis zum Ende des Zuges.","texto":"Nur der Krieger, der sterbliche Schw\u00e4che zugibt, kann unsterbliche St\u00e4rke erhalten.","tipos":["Hexerei"],"legalidade":["Legal in Vintage (Type 1)","Legal in Legacy (Type 1.5)","Legal in Classic (MTGO)","Legal in Commander","Legal in Modern"],"regras":[""],"_id":{"$id":"539eff762a6931b00fddce92"}},"2":{"numero":2,"sigla_edicao":"st2k","edicao":"Starter 2000","cod":"2st2kde","idioma":"de","nome":"Lebenshauch","ataque":"","resistencia":"","lealdade":"","mana":"3W","mana_convertida":"4","raridade":"Special","artista":"DiTerlizzi","link":"http:\/\/magiccards.info\/st2k\/de\/2.html","imagem_src":"http:\/\/magiccards.info\/scans\/de\/st2k\/2.jpg","imagem_local":"st2k\/de\/2.jpg","descricao":"Bringe eine Kreaturenkarte Deiner Wahl aus Deinem Friedhof direkt ins Spiel.","texto":"","tipos":["Hexerei"],"legalidade":["Legal in Vintage (Type 1)","Legal in Legacy (Type 1.5)","Legal in Classic (MTGO)","Legal in Commander"],"regras":[""],"_id":{"$id":"539eff762a6931b00fddce93"}},"3":{"numero":3,"sigla_edicao":"st2k","edicao":"Starter 2000","cod":"3st2kde","idioma":"de","nome":"D\u00fcsterwaldkeiler","ataque":"4","resistencia":"4","lealdade":"","mana":"4G","mana_convertida":"5","raridade":"Special","artista":"Mike Kimble","link":"http:\/\/magiccards.info\/st2k\/de\/3.html","imagem_src":"http:\/\/magiccards.info\/scans\/de\/st2k\/3.jpg","imagem_local":"st2k\/de\/3.jpg","descricao":"","texto":"\"Und heraus fuhr der Wirrgeist, hinein in die Schweine, und die Herde raste den Abhang hinab.\"\r\n\u2014 Die Bibel, Markus 5:13\"","tipos":["Wildschwein","Kreatur"],"legalidade":["Legal in Vintage (Type 1)","Legal in Legacy (Type 1.5)","Legal in Commander"],"regras":[""],"_id":{"$id":"539eff762a6931b00fddce94"}},"4":{"numero":4,"sigla_edicao":"st2k","edicao":"Starter 2000","cod":"4st2kde","idioma":"de","nome":"Eifriger Kadett","ataque":"1","resistencia":"1","lealdade":"","mana":"W","mana_convertida":"1","raridade":"Special","artista":"Scott M. Fischer","link":"http:\/\/magiccards.info\/st2k\/de\/4.html","imagem_src":"http:\/\/magiccards.info\/scans\/de\/st2k\/4.jpg","imagem_local":"st2k\/de\/4.jpg","descricao":"","texto":"Der Eifer der Jugend, gesch\u00e4rft durch die Disziplin der Soldatenausbildung.","tipos":["Soldat","Kreatur"],"legalidade":["Legal in Vintage (Type 1)","Legal in Legacy (Type 1.5)","Legal in Classic (MTGO)","Legal in Commander","Legal in Modern"],"regras":[""],"_id":{"$id":"539eff762a6931b00fddce95"}},"5":{"numero":5,"sigla_edicao":"st2k","edicao":"Starter 2000","cod":"5st2kde","idioma":"de","nome":"Riesenoktopus","ataque":"3","resistencia":"3","lealdade":"","mana":"3U","mana_convertida":"4","raridade":"Special","artista":"John Matson","link":"http:\/\/magiccards.info\/st2k\/de\/5.html","imagem_src":"http:\/\/magiccards.info\/scans\/de\/st2k\/5.jpg","imagem_local":"st2k\/de\/5.jpg","descricao":"","texto":"Beim Anblick des Tieres wurden die Augen des Tintenfischverk\u00e4ufers gro\u00df, doch niemand vermochte zu sagen, ob aus Angst oder aus Habgier.","tipos":["Oktopus","Kreatur"],"legalidade":["Legal in Vintage (Type 1)","Legal in Legacy (Type 1.5)","Legal in Classic (MTGO)","Legal in Commander","Legal in Modern"],"regras":[""],"_id":{"$id":"539eff762a6931b00fddce96"}},"6":{"numero":6,"sigla_edicao":"st2k","edicao":"Starter 2000","cod":"6st2kde","idioma":"de","nome":"Todbringende Hand","ataque":"","resistencia":"","lealdade":"","mana":"2B","mana_convertida":"3","raridade":"Special","artista":"Heather Hudson","link":"http:\/\/magiccards.info\/st2k\/de\/6.html","imagem_src":"http:\/\/magiccards.info\/scans\/de\/st2k\/6.jpg","imagem_local":"st2k\/de\/6.jpg","descricao":"Zerst\u00f6re eine nichtschwarze Kreatur Deiner Wahl.","texto":"Die Ber\u00fchrung des Todes ist niemals sanft.","tipos":["Hexerei"],"legalidade":["Legal in Vintage (Type 1)","Legal in Legacy (Type 1.5)","Legal in Commander"],"regras":[""],"_id":{"$id":"539eff762a6931b00fddce97"}},"7":{"numero":7,"sigla_edicao":"st2k","edicao":"Starter 2000","cod":"7st2kde","idioma":"de","nome":"Fahrender Ritter","ataque":"2","resistencia":"2","lealdade":"","mana":"1W","mana_convertida":"2","raridade":"Special","artista":"Dan Frazier","link":"http:\/\/magiccards.info\/st2k\/de\/7.html","imagem_src":"http:\/\/magiccards.info\/scans\/de\/st2k\/7.jpg","imagem_local":"st2k\/de\/7.jpg","descricao":"","texto":"\"... und der Ehre geht die Demut voran.\"\r\n\u2014 Die Bibel, Spr\u00fcche 15:33\"","tipos":["Ritter","Kreatur"],"legalidade":["Legal in Vintage (Type 1)","Legal in Legacy (Type 1.5)","Legal in Classic (MTGO)","Legal in Commander"],"regras":[""],"_id":{"$id":"539eff762a6931b00fddce98"}},"8":{"numero":8,"sigla_edicao":"st2k","edicao":"Starter 2000","cod":"8st2kde","idioma":"de","nome":"Lavaaxt","ataque":"","resistencia":"","lealdade":"","mana":"4R","mana_convertida":"5","raridade":"Special","artista":"Brian Sn\u00f5ddy","link":"http:\/\/magiccards.info\/st2k\/de\/8.html","imagem_src":"http:\/\/magiccards.info\/scans\/de\/st2k\/8.jpg","imagem_local":"st2k\/de\/8.jpg","descricao":"Die Lavaaxt f\u00fcgt einem Gegner Deiner Wahl 5 Schadenspunkte zu.","texto":"Sie soll sich durch den K\u00f6rper brennen, bis direkt in die Seele hinein.","tipos":["Hexerei"],"legalidade":["Legal in Vintage (Type 1)","Legal in Legacy (Type 1.5)","Legal in Extended (Type 1.X)","Legal in Standard (Type 2)","Legal in Classic (MTGO)","Legal in Commander","Legal in Modern"],"regras":[""],"_id":{"$id":"539eff762a6931b00fddce99"}},"9":{"numero":9,"sigla_edicao":"st2k","edicao":"Starter 2000","cod":"9st2kde","idioma":"de","nome":"Mons' pl\u00fcndernde Goblins","ataque":"1","resistencia":"1","lealdade":"","mana":"R","mana_convertida":"1","raridade":"Special","artista":"Pete Venters","link":"http:\/\/magiccards.info\/st2k\/de\/9.html","imagem_src":"http:\/\/magiccards.info\/scans\/de\/st2k\/9.jpg","imagem_local":"st2k\/de\/9.jpg","descricao":"","texto":"Sp\u00fcrst Du ihre Keule, kriegst Du meist 'ne Beule.","tipos":["Goblin","Kreatur"],"legalidade":["Legal in Vintage (Type 1)","Legal in Legacy (Type 1.5)","Legal in Commander"],"regras":[""],"_id":{"$id":"539eff762a6931b00fddce9a"}},"10":{"numero":10,"sigla_edicao":"st2k","edicao":"Starter 2000","cod":"10st2kde","idioma":"de","nome":"Unheimliches Wachstum","ataque":"","resistencia":"","lealdade":"","mana":"1G","mana_convertida":"2","raridade":"Special","artista":"Una Fricker","link":"http:\/\/magiccards.info\/st2k\/de\/10.html","imagem_src":"http:\/\/magiccards.info\/scans\/de\/st2k\/10.jpg","imagem_local":"st2k\/de\/10.jpg","descricao":"Eine Kreatur Deiner Wahl erh\u00e4lt +4\/+4 bis zum Ende des Zuges.","texto":"\"Das kleine \"Eichhorn-\u00e4rger-dich-nicht\"-Spiel der Nachtschrate nahm eine unerwartete Wendung.\"","tipos":["Hexerei"],"legalidade":["Legal in Vintage (Type 1)","Legal in Legacy (Type 1.5)","Legal in Classic (MTGO)","Legal in Commander","Legal in Modern"],"regras":[""],"_id":{"$id":"539eff762a6931b00fddce9b"}},"11":{"numero":11,"sigla_edicao":"st2k","edicao":"Starter 2000","cod":"11st2kde","idioma":"de","nome":"Mondfee","ataque":"1","resistencia":"1","lealdade":"","mana":"1G","mana_convertida":"2","raridade":"Special","artista":"Terese Nielsen","link":"http:\/\/magiccards.info\/st2k\/de\/11.html","imagem_src":"http:\/\/magiccards.info\/scans\/de\/st2k\/11.jpg","imagem_local":"st2k\/de\/11.jpg","descricao":"Fliegend","texto":"\"Ich bin der fr\u00f6hliche Wanderer der Nacht.\"\r\n\u2014 William Shakespeare, Ein Sommernachtstraum\"","tipos":["Feenwesen","Kreatur"],"legalidade":["Legal in Vintage (Type 1)","Legal in Legacy (Type 1.5)","Legal in Commander"],"regras":[""],"_id":{"$id":"539eff762a6931b00fddce9c"}},"12":{"numero":12,"sigla_edicao":"st2k","edicao":"Starter 2000","cod":"12st2kde","idioma":"de","nome":"Ogerkrieger","ataque":"3","resistencia":"3","lealdade":"","mana":"3R","mana_convertida":"4","raridade":"Special","artista":"Jeff Miracola","link":"http:\/\/magiccards.info\/st2k\/de\/12.html","imagem_src":"http:\/\/magiccards.info\/scans\/de\/st2k\/12.jpg","imagem_local":"st2k\/de\/12.jpg","descricao":"","texto":"Hier mu\u00df man nicht um Schl\u00e4ge betteln.","tipos":["Oger","Kreatur"],"legalidade":["Legal in Vintage (Type 1)","Legal in Legacy (Type 1.5)","Legal in Commander"],"regras":[""],"_id":{"$id":"539eff762a6931b00fddce9d"}},"13":{"numero":13,"sigla_edicao":"st2k","edicao":"Starter 2000","cod":"13st2kde","idioma":"de","nome":"Rhox","ataque":"5","resistencia":"5","lealdade":"","mana":"4GG","mana_convertida":"6","raridade":"Special","artista":"Mark Zug","link":"http:\/\/magiccards.info\/st2k\/de\/13.html","imagem_src":"http:\/\/magiccards.info\/scans\/de\/st2k\/13.jpg","imagem_local":"st2k\/de\/13.jpg","descricao":"Du kannst Rhox Kampfschaden dem verteidigenden Spieler zuf\u00fcgen lassen, als ob er nicht geblockt worden w\u00e4re.\r\n\r\n{2}{G}: Regeneriere Rhox.","texto":"","tipos":["Bestie","Kreatur"],"legalidade":["Legal in Vintage (Type 1)","Legal in Legacy (Type 1.5)","Legal in Classic (MTGO)","Legal in Commander","Legal in Modern"],"regras":[{"data":"4\/1\/2008","texto":" If this creature is attacking a planeswalker, assigning its damage as though it weren't blocked means the damage is assigned to the planeswalker, not to the defending player."},{"data":"4\/1\/2008","texto":" When assigning combat damage, you choose whether you want to assign all damage to blocking creatures, or if you want to assign all of it to the defending player or planeswalker. You can't split the damage assignment between them."},{"data":"4\/1\/2008","texto":" You can decide to assign damage to the defending player or planeswalker even if the blocking creature has protection from green or damage preventing effects on it."},{"data":"4\/1\/2008","texto":" If blocked by a creature with banding, the defending player decides whether or not the damage is assigned \"as though it weren't blocked\"."}],"_id":{"$id":"539eff762a6931b00fddce9e"}},"14":{"numero":14,"sigla_edicao":"st2k","edicao":"Starter 2000","cod":"14st2kde","idioma":"de","nome":"K\u00f6nigsfalke","ataque":"1","resistencia":"1","lealdade":"","mana":"1W","mana_convertida":"2","raridade":"Special","artista":"Carl Critchlow","link":"http:\/\/magiccards.info\/st2k\/de\/14.html","imagem_src":"http:\/\/magiccards.info\/scans\/de\/st2k\/14.jpg","imagem_local":"st2k\/de\/14.jpg","descricao":"Fliegend","texto":"Aus Instinkt ein J\u00e4ger, trainiert eine Waffe.","tipos":["Vogel","Kreatur"],"legalidade":["Legal in Vintage (Type 1)","Legal in Legacy (Type 1.5)","Legal in Commander"],"regras":[""],"_id":{"$id":"539eff762a6931b00fddce9f"}},"15":{"numero":15,"sigla_edicao":"st2k","edicao":"Starter 2000","cod":"15st2kde","idioma":"de","nome":"Seeadler","ataque":"1","resistencia":"1","lealdade":"","mana":"1U","mana_convertida":"2","raridade":"Special","artista":"Anthony S. Waters","link":"http:\/\/magiccards.info\/st2k\/de\/15.html","imagem_src":"http:\/\/magiccards.info\/scans\/de\/st2k\/15.jpg","imagem_local":"st2k\/de\/15.jpg","descricao":"Fliegend","texto":"Wo Luft und Wasser aufeinandertreffen, klauen Klauen Fische.","tipos":["Vogel","Kreatur"],"legalidade":["Legal in Vintage (Type 1)","Legal in Legacy (Type 1.5)","Legal in Classic (MTGO)","Legal in Commander","Legal in Modern"],"regras":[""],"_id":{"$id":"539eff762a6931b00fddcea0"}},"16":{"numero":16,"sigla_edicao":"st2k","edicao":"Starter 2000","cod":"16st2kde","idioma":"de","nome":"Zeitebbe","ataque":"","resistencia":"","lealdade":"","mana":"2U","mana_convertida":"3","raridade":"Special","artista":"Alan Rabinowitz","link":"http:\/\/magiccards.info\/st2k\/de\/16.html","imagem_src":"http:\/\/magiccards.info\/scans\/de\/st2k\/16.jpg","imagem_local":"st2k\/de\/16.jpg","descricao":"Lege eine Kreatur Deiner Wahl oben auf die Bibliothek ihres Besitzers zur\u00fcck.","texto":"Wie die Gezeiten, so hat auch die Zeit einen wechselnden Verlauf.","tipos":["Hexerei"],"legalidade":["Legal in Vintage (Type 1)","Legal in Legacy (Type 1.5)","Legal in Extended (Type 1.X)","Legal in Standard (Type 2)","Legal in Classic (MTGO)","Legal in Commander","Legal in Modern"],"regras":[""],"_id":{"$id":"539eff762a6931b00fddcea1"}},"17":{"numero":17,"sigla_edicao":"st2k","edicao":"Starter 2000","cod":"17st2kde","idioma":"de","nome":"Trainierter Orgg","ataque":"6","resistencia":"6","lealdade":"","mana":"6R","mana_convertida":"7","raridade":"Special","artista":"Eric Peterson","link":"http:\/\/magiccards.info\/st2k\/de\/17.html","imagem_src":"http:\/\/magiccards.info\/scans\/de\/st2k\/17.jpg","imagem_local":"st2k\/de\/17.jpg","descricao":"","texto":"Grunds\u00e4tzlich wissen Orggs, wie man t\u00f6tet.\r\nWas man t\u00f6ten soll, mu\u00df man ihnen beibringen.","tipos":["Bestie","Kreatur"],"legalidade":["Legal in Vintage (Type 1)","Legal in Legacy (Type 1.5)","Legal in Classic (MTGO)","Legal in Commander"],"regras":[""],"_id":{"$id":"539eff762a6931b00fddcea2"}},"18":{"numero":18,"sigla_edicao":"st2k","edicao":"Starter 2000","cod":"18st2kde","idioma":"de","nome":"Vizzerdrix","ataque":"6","resistencia":"6","lealdade":"","mana":"6U","mana_convertida":"7","raridade":"Special","artista":"Eric Peterson","link":"http:\/\/magiccards.info\/st2k\/de\/18.html","imagem_src":"http:\/\/magiccards.info\/scans\/de\/st2k\/18.jpg","imagem_local":"st2k\/de\/18.jpg","descricao":"","texto":"Das Ding, das aus dem Sumpf kam, mag gemeiner sein, aber der Vizzerdrix ist viel gr\u00f6\u00dfer.","tipos":["Bestie","Kreatur"],"legalidade":["Legal in Vintage (Type 1)","Legal in Legacy (Type 1.5)","Legal in Classic (MTGO)","Legal in Commander","Legal in Modern"],"regras":[""],"_id":{"$id":"539eff762a6931b00fddcea3"}},"19":{"numero":19,"sigla_edicao":"st2k","edicao":"Starter 2000","cod":"19st2kde","idioma":"de","nome":"Wildgreif","ataque":"2","resistencia":"2","lealdade":"","mana":"2W","mana_convertida":"3","raridade":"Special","artista":"Jeff Miracola","link":"http:\/\/magiccards.info\/st2k\/de\/19.html","imagem_src":"http:\/\/magiccards.info\/scans\/de\/st2k\/19.jpg","imagem_local":"st2k\/de\/19.jpg","descricao":"Fliegend","texto":"Ein Ork und ein Goblin spielten im Hain \u2014 dann kam der Wildgreif und der Ork war allein.","tipos":["Greif","Kreatur"],"legalidade":["Legal in Vintage (Type 1)","Legal in Legacy (Type 1.5)","Legal in Classic (MTGO)","Legal in Commander","Legal in Modern"],"regras":[""],"_id":{"$id":"539eff762a6931b00fddcea4"}},"20":{"numero":20,"sigla_edicao":"st2k","edicao":"Starter 2000","cod":"20st2kde","idioma":"de","nome":"Weidenelf","ataque":"1","resistencia":"1","lealdade":"","mana":"G","mana_convertida":"1","raridade":"Special","artista":"DiTerlizzi","link":"http:\/\/magiccards.info\/st2k\/de\/20.html","imagem_src":"http:\/\/magiccards.info\/scans\/de\/st2k\/20.jpg","imagem_local":"st2k\/de\/20.jpg","descricao":"","texto":"Der Wald lebt im Elfen wie der Elf im Walde.","tipos":["Elf","Kreatur"],"legalidade":["Legal in Vintage (Type 1)","Legal in Legacy (Type 1.5)","Legal in Commander"],"regras":[""],"_id":{"$id":"539eff762a6931b00fddcea5"}}}}